myProjectThatIWantUploaded/__init__.py
awesome_pypi_package2-0.0.2.dist-info/LICENSE
awesome_pypi_package2-0.0.2.dist-info/METADATA
awesome_pypi_package2-0.0.2.dist-info/WHEEL
awesome_pypi_package2-0.0.2.dist-info/top_level.txt
awesome_pypi_package2-0.0.2.dist-info/RECORD
