Metadata-Version: 2.1
Name: awesome-pypi-package2
Version: 0.0.2
Summary: my short description
Author-email: Olliver Aira <olliver.aira@gmail.com>
License-File: LICENSE
